napalm_pluribus
