Metadata-Version: 1.1
Name: napalm-pluribus
Version: 0.4.2
Summary: Network Automation and Programmability Abstraction Layer with Multivendor support
Home-page: https://github.com/napalm-automation/napalm-pluribus
Author: David Barroso, Mircea Ulinic
Author-email: dbarrosop@dravetech.com, mircea@cloudflare.com
License: UNKNOWN
Platform: UNKNOWN
Classifier: Topic :: Utilities
Classifier: Programming Language :: Python
Classifier: Operating System :: POSIX :: Linux
Classifier: Operating System :: MacOS
